{
    "/build/assets/app.js": "/build/assets/app.js",
    "/build/assets/m_main.css": "/build/assets/m_main.css",
    "/build/assets/d_productCard.css": "/build/assets/d_productCard.css",
    "/build/assets/d_footer.css": "/build/assets/d_footer.css",
    "/build/assets/d_hero.css": "/build/assets/d_hero.css",
    "/build/assets/d_main.css": "/build/assets/d_main.css",
    "/build/assets/m_footer.css": "/build/assets/m_footer.css",
    "/build/assets/m_productCard.css": "/build/assets/m_productCard.css",
    "/build/assets/m_hero.css": "/build/assets/m_hero.css",
    "/build/assets/m_searchBar.css": "/build/assets/m_searchBar.css"
}
